autarco/__init__.py
autarco/autarco.py
autarco/exceptions.py
autarco/models.py
autarco/py.typed
autarco-3.1.0.dist-info/LICENSE
autarco-3.1.0.dist-info/METADATA
autarco-3.1.0.dist-info/WHEEL
autarco-3.1.0.dist-info/RECORD
