Metadata-Version: 2.1
Name: autarco
Version: 3.1.0
Summary: Asynchronous Python client for the Autarco Inverters
Home-page: https://github.com/klaasnicolaas/python-autarco
License: MIT
Keywords: autarco,inverter,power,energy,async,client
Author: Klaas Schoute
Author-email: hello@student-techlife.com
Maintainer: Klaas Schoute
Maintainer-email: hello@student-techlife.com
Requires-Python: >=3.11,<4.0
Classifier: Framework :: AsyncIO
Classifier: Intended Audience :: Developers
Classifier: License :: OSI Approved :: MIT License
Classifier: Natural Language :: English
Classifier: Programming Language :: Python :: 3
Classifier: Programming Language :: Python :: 3.11
Classifier: Programming Language :: Python :: 3.12
Classifier: Programming Language :: Python :: 3.13
Classifier: Topic :: Software Development :: Libraries :: Python Modules
Requires-Dist: aiohttp (>=3.0.0)
Requires-Dist: mashumaro (>=3.12,<4.0)
Requires-Dist: orjson (>=3.9.14,<4.0.0)
Requires-Dist: yarl (>=1.6.0)
Project-URL: Bug Tracker, https://github.com/klaasnicolaas/python-autarco/issues
Project-URL: Changelog, https://github.com/klaasnicolaas/python-autarco/releases
Project-URL: Documentation, https://github.com/klaasnicolaas/python-autarco
Project-URL: Repository, https://github.com/klaasnicolaas/python-autarco
